setup.py
Thorium.egg-info/PKG-INFO
Thorium.egg-info/SOURCES.txt
Thorium.egg-info/dependency_links.txt
Thorium.egg-info/requires.txt
Thorium.egg-info/top_level.txt
thorium/__init__.py
thorium/auth.py
thorium/autorestdoc.py
thorium/crossdomain_decorator.py
thorium/datastructures.py
thorium/dispatcher.py
thorium/endpoint.py
thorium/errors.py
thorium/exception_handler.py
thorium/fields.py
thorium/logging.py
thorium/parameters.py
thorium/params.py
thorium/request.py
thorium/resources.py
thorium/response.py
thorium/routing.py
thorium/serializer.py
thorium/thorium.py
thorium/thoriumflask.py
thorium/validators.py
thorium/ext/__init__.py