Metadata-Version: 1.1
Name: Thorium
Version: 0.2.12
Summary: A Python framework for RESTful API interfaces in Flask
Home-page: https://github.com/EventMobi/thorium
Author: Ryan Easterbrook
Author-email: ryan@eventmobi.com
License: BSD
Platform: UNKNOWN
Classifier: Framework :: Flask
Classifier: Intended Audience :: Developers
Classifier: License :: OSI Approved :: BSD License
Classifier: Programming Language :: Python :: 3
